benfordviz/__init__.py
benfordviz/bokeh_plotting.py
benfordviz/bokeh_utils.py
benfordviz/checks.py
benfordviz/config.py
benfordviz/constants.py
benfordviz/core.py
benfordviz/utils.py
benfordviz-0.2.0.dist-info/LICENSE.txt
benfordviz-0.2.0.dist-info/METADATA
benfordviz-0.2.0.dist-info/WHEEL
benfordviz-0.2.0.dist-info/top_level.txt
benfordviz-0.2.0.dist-info/RECORD
