Metadata-Version: 2.1
Name: benfordviz
Version: 0.2.0
Summary: A library providing interactive plotting to benford-py
Home-page: https://github.com/milcent/benfordviz
Author: Marcel Milcent
Author-email: marcelmilcent@gmail.com
License: BSD 3-Clause
Download-URL: https://github.com/milcent/benfordviz/archive/v0.2.0.tar.gz
Platform: UNKNOWN
Classifier: Programming Language :: Python :: 3
Classifier: License :: OSI Approved :: BSD License
Classifier: Natural Language :: English
Classifier: Operating System :: OS Independent
Classifier: Development Status :: 2 - Pre-Alpha
Classifier: Intended Audience :: Financial and Insurance Industry
Classifier: Intended Audience :: Science/Research
Classifier: Intended Audience :: Education
Classifier: Intended Audience :: Other Audience
Classifier: Topic :: Office/Business :: Financial :: Accounting
Classifier: Topic :: Scientific/Engineering :: Mathematics
License-File: LICENSE.txt
Requires-Dist: benford-py
Requires-Dist: bokeh (>=2.2.2)
